ds_discovery/__init__.py
ds_discovery/__pycache__/__init__.cpython-310.pyc
ds_discovery/components/__init__.py
ds_discovery/components/abstract_common_component.py
ds_discovery/components/commons.py
ds_discovery/components/concept_tolerance.py
ds_discovery/components/controller.py
ds_discovery/components/discovery.py
ds_discovery/components/event_book_portfolio.py
ds_discovery/components/feature_catalog.py
ds_discovery/components/models_builder.py
ds_discovery/components/synthetic_builder.py
ds_discovery/components/transitioning.py
ds_discovery/components/wrangling.py
ds_discovery/engines/__init__.py
ds_discovery/engines/events/__init__.py
ds_discovery/engines/events/event_book_controller.py
ds_discovery/engines/events/pandas_event_book.py
ds_discovery/engines/executor/__init__.py
ds_discovery/engines/executor/src/__init__.py
ds_discovery/engines/executor/src/hadron_executor.py
ds_discovery/handlers/__init__.py
ds_discovery/handlers/event_handlers.py
ds_discovery/handlers/pandas_handlers.py
ds_discovery/handlers/pandas_pubsub.py
ds_discovery/handlers/s3_handlers.py
ds_discovery/intent/__init__.py
ds_discovery/intent/abstract_builder_correlate_intent.py
ds_discovery/intent/abstract_builder_frame_intent.py
ds_discovery/intent/abstract_builder_get_intent.py
ds_discovery/intent/abstract_builder_intent.py
ds_discovery/intent/abstract_builder_model_intent.py
ds_discovery/intent/abstract_common_intent.py
ds_discovery/intent/concept_tolerance_intent.py
ds_discovery/intent/controller_intent.py
ds_discovery/intent/event_book_intent.py
ds_discovery/intent/feature_catalog_intent.py
ds_discovery/intent/models_intent.py
ds_discovery/intent/synthetic_intent.py
ds_discovery/intent/transition_intent.py
ds_discovery/intent/wrangle_intent.py
ds_discovery/intent/__pycache__/__init__.cpython-310.pyc
ds_discovery/intent/__pycache__/synthetic_intent.cpython-310.pyc
ds_discovery/managers/__init__.py
ds_discovery/managers/concept_tolerance_property_manager.py
discovery_transition_ds-4.18.14.dist-info/LICENSE.txt
discovery_transition_ds-4.18.14.dist-info/METADATA
discovery_transition_ds-4.18.14.dist-info/WHEEL
discovery_transition_ds-4.18.14.dist-info/top_level.txt
discovery_transition_ds-4.18.14.dist-info/RECORD
