Metadata-Version: 2.1
Name: discovery-transition-ds
Version: 4.18.14
Summary: Data Science to production accelerator
Home-page: https://github.com/gigas64/discovery-transition-ds
Author: Gigas64
Author-email: gigas64@opengrass.net
License: BSD
Keywords: Wrangling ML Visualisation Dictionary Discovery Productize Classification Feature Engineering Cleansing
Classifier: Development Status :: 5 - Production/Stable
Classifier: License :: OSI Approved :: BSD License
Classifier: Intended Audience :: Developers
Classifier: Intended Audience :: Science/Research
Classifier: Programming Language :: Python :: 3.7
Classifier: Programming Language :: Python :: 3.8
Classifier: Programming Language :: Python :: 3.9
Classifier: Topic :: Adaptive Technologies
Classifier: Topic :: Scientific/Engineering :: Artificial Intelligence
Classifier: Topic :: Scientific/Engineering :: Information Analysis
Classifier: Topic :: Software Development :: Libraries :: Python Modules
Requires-Python: >=3.7
License-File: LICENSE.txt
Requires-Dist: aistac-foundation
Requires-Dist: discovery-connectors
Requires-Dist: pandas
Requires-Dist: numpy
Requires-Dist: matplotlib
Requires-Dist: seaborn
Requires-Dist: scikit-learn
Requires-Dist: scipy
Requires-Dist: boto3
Requires-Dist: botocore
Requires-Dist: fsspec
Requires-Dist: s3fs
Requires-Dist: pyyaml
